MANIFEST.in
PYPI_VERSION
README.md
setup.cfg
setup.py
bin/__init__.py
bin/now-playing-unused.py
bin/now-playing.py
pi3dpf_ns/__init__.py
pi3dpf_ns/pi3dpf_np/__init__.py
pi3dpf_ns/pi3dpf_np/alexa/__init__.py
pi3dpf_ns/pi3dpf_np/alexa/alexa.py
pi3dpf_ns/pi3dpf_np/alexa/echo.py
pi3dpf_ns/pi3dpf_np/alexa/muteAdverts.py
pi3dpf_ns/pi3dpf_np/alexa/visualize.py
pi3dpf_ns/pi3dpf_np/alexa/js/ajax-interceptor.js
pi3dpf_ns/pi3dpf_np/alexa/js/nfo/XMLHttpRequest.reponse.devices.txt
pi3dpf_ns/pi3dpf_np/alexa/js/nfo/XMLHttpRequest.reponse.playerInfo.txt
pi3dpf_ns/pi3dpf_np/alexa/js/nfo/XMLHttpRequest.reponse.primeMusicBrowseable.txt
pi3dpf_ns/pi3dpf_np/alexa/js/nfo/XMLHttpRequest.reponse.queueInfo.txt
pi3dpf_ns/pi3dpf_np/cfg/now-playing-skills.config
pi3dpf_ns/pi3dpf_np/cfg/np.config
pi3dpf_ns/pi3dpf_np/cfg/fonts/NotoSans-Condensed.ttf
pi3dpf_ns/pi3dpf_np/cfg/icons/1x1-transparent.png
pi3dpf_ns/pi3dpf_np/cfg/icons/Broken-image-389560-black.png
pi3dpf_ns/pi3dpf_np/cfg/icons/Broken-image-389560-black.svg
pi3dpf_ns/pi3dpf_np/cfg/icons/Broken-image-389560-white.png
pi3dpf_ns/pi3dpf_np/cfg/icons/Broken-image-389560-white.svg
pi3dpf_ns/pi3dpf_np/cfg/icons/Broken-image-389560.svg
pi3dpf_ns/pi3dpf_np/cfg/icons/Pause_-_The_Noun_Project-black.png
pi3dpf_ns/pi3dpf_np/cfg/icons/Pause_-_The_Noun_Project-black.svg
pi3dpf_ns/pi3dpf_np/cfg/icons/Pause_-_The_Noun_Project-white.png
pi3dpf_ns/pi3dpf_np/cfg/icons/Pause_-_The_Noun_Project-white.svg
pi3dpf_ns/pi3dpf_np/cfg/icons/attribution.txt
pi3dpf_ns/pi3dpf_np/cfg/icons/broken_image-24px.svg
pi3dpf_ns/pi3dpf_np/common.x/__init__.py
pi3dpf_ns/pi3dpf_np/common.x/pf_common.py
pi3dpf_ns/pi3dpf_np/plex/__init__.py
pi3dpf_ns/pi3dpf_np/plex/plex-now-playing-demo.py
pi3dpf_ns/pi3dpf_np/plex/plex.py
pi3dpf_ns/pi3dpf_np/sonos/__init__.py
pi3dpf_ns/pi3dpf_np/sonos/sonos.py
pi3dpf_ns/pi3dpf_np/tunein/__init__.py
pi3dpf_ns/pi3dpf_np/tunein/icy_tags.py
pi3dpf_ns/pi3dpf_np/tunein/tunein.py
pi3dpf_ns/pi3dpf_np/tunein/tunejack.sh
pi3dpf_ns_pi3dpf_np.egg-info/PKG-INFO
pi3dpf_ns_pi3dpf_np.egg-info/SOURCES.txt
pi3dpf_ns_pi3dpf_np.egg-info/dependency_links.txt
pi3dpf_ns_pi3dpf_np.egg-info/not-zip-safe
pi3dpf_ns_pi3dpf_np.egg-info/requires.txt
pi3dpf_ns_pi3dpf_np.egg-info/top_level.txt